pygame_utils/__init__.py
pygame_utils/sceneman.py
pygame_utils/threed.py
pygame_utils/utils.py
pygame_utils-0.3.0.dist-info/WHEEL
pygame_utils-0.3.0.dist-info/METADATA
pygame_utils-0.3.0.dist-info/RECORD
