Metadata-Version: 2.1
Name: pygame-utils
Version: 0.3.0
Summary: 
Author: Nathan Strong
Author-email: nathanstrong777@gmail.com
Requires-Python: >=3.8,<4.0
Classifier: Programming Language :: Python :: 3
Classifier: Programming Language :: Python :: 3.10
Classifier: Programming Language :: Python :: 3.8
Classifier: Programming Language :: Python :: 3.9
Requires-Dist: pygame (>=2.1.2,<3.0.0)
